minchin/pelican/plugins/optimize_images.py
minchin_pelican_plugins_optimize_images-1.3.0.dist-info/licenses/LICENSE.txt
minchin_pelican_plugins_optimize_images-1.3.0.dist-info/METADATA
minchin_pelican_plugins_optimize_images-1.3.0.dist-info/WHEEL
minchin_pelican_plugins_optimize_images-1.3.0.dist-info/top_level.txt
minchin_pelican_plugins_optimize_images-1.3.0.dist-info/RECORD
