Metadata-Version: 2.4
Name: minchin.pelican.plugins.optimize_images
Version: 1.3.0
Summary: This Pelican plugin optimizes images (jpg and png).
Author-email: William Minchin <w_minchin@hotmail.com>
Maintainer-email: William Minchin <w_minchin@hotmail.com>
License-Expression: AGPL-3.0-only
Project-URL: Bug Tracker, https://github.com/MinchinWeb/minchin.pelican.plugins.optimize_images/issues
Project-URL: Repository, https://github.com/MinchinWeb/minchin.pelican.plugins.optimize_images
Project-URL: Changelog, https://github.com/minchinweb/minchin.pelican.plugins.optimize_images/blob/master/CHANGELOG.rst
Classifier: Development Status :: 5 - Production/Stable
Classifier: Environment :: Console
Classifier: Framework :: Pelican :: Plugins
Classifier: Programming Language :: Python :: 3
Classifier: Programming Language :: Python :: 3.9
Classifier: Programming Language :: Python :: 3.10
Classifier: Programming Language :: Python :: 3.11
Classifier: Programming Language :: Python :: 3.12
Classifier: Programming Language :: Python :: 3.13
Classifier: Programming Language :: Python :: 3 :: Only
Classifier: Natural Language :: English
Classifier: Intended Audience :: Developers
Classifier: Operating System :: OS Independent
Classifier: Topic :: Software Development :: Libraries :: Python Modules
License-File: LICENSE.txt
Requires-Dist: pelican
Requires-Dist: minchin.pelican.plugins.autoloader>=1.2.0
Provides-Extra: build
Requires-Dist: pip-tools; extra == "build"
Requires-Dist: minchin.releaser>=0.8.2; extra == "build"
Provides-Extra: docs
Provides-Extra: test
Dynamic: license-file
